<?xml version="1.0" encoding="UTF-8"?>
<!--Sample XML file generated by XMLSpy v2013 sp1 (http://www.altova.com)-->
<DocumentReference xmlns="http://hl7.org/fhir" xmlns:xsi="http://www.w3.org/2001/XMLSchema-instance" xsi:schemaLocation="http://hl7.org/fhir fhir-all-xsd/documentreference.xsd">
	<id value="1.2.276.0.7230010.3.1.3.1787205428.3112.1522315594.397907"/>
	
<masterIdentifier>
		<system value="urn:ietf:rfc:3986"/>
		<value value="urn:oid:1.3.12.2.1107.5.6.1.12345.30100106121215554978100000005"/>
	</masterIdentifier>
	<status value="current"/>
	
	<!-- LEFT BECAUSE IT IS REQUIRED HOW OT VALORIZE THE DOCUMENT TYPE ? 

FOR THE TIME BEING VALORIZED AS "Best illustration of finding" BUT NOT SUR EIS SEMANTICALLY CORRECT  (TYPE OF RELATIONSHIP ?) 

-->
	<type>
		<coding>
					<system value="http://dicom.nema.org/resources/ontology/DCM"/>
					<code value="121080"/>
					<display value="Best illustration of finding"/>
		</coding>
	</type>
	
	<indexed value="2017-12-15T09:30:47Z"/>
	<content>
		<attachment>
		<extension url="http://trilliumbridge.eu/fhir/StructureDefinition/ihexdsidentifiers-uv-trillium2">
		<extension url="homeCommunityID">
		<valueId value="1.2.276.0.7230010.3.1.2.1787205428.3090.1522315440.525661"/></extension>
		<extension url="XDSRepositoryUID">
<valueId value="1.2.276.0.7230010.3.1.4.1787205428.3085.1522315419.821823"/>		
		</extension>		
		
		</extension>
			<extension url="accessProtocol">
				<valueCodeableConcept>
					<coding>
						<system value="http://trilliumbridge.eu/fhir/CodeSystem/trilm2-codesystem-1"/>
						<code value="XCA"/>
						<display value="IHE Cross-community Access"/>
					</coding>
				</valueCodeableConcept>
			</extension>
			<contentType value="application/dicom"/>
			<size value="3230"/>
			<creation value="2017-12-15"/>
		</attachment>
	</content>
</DocumentReference>
