<?xml version="1.0" encoding="UTF-8"?>
<!--Sample XML file generated by XMLSpy v2013 sp1 (http://www.altova.com)-->
<DocumentReference xmlns="http://hl7.org/fhir" xmlns:xsi="http://www.w3.org/2001/XMLSchema-instance" xsi:schemaLocation="http://hl7.org/fhir file:///C:/Users/Giorgio/Dropbox/_Consulenze/__Trillium/___Trillium_II/___FHIR/Examples/fhir-all-xsd/documentreference.xsd">
	<id value="TII-DocumentReference-1"/>
	<masterIdentifier>
		<system value="urn:ietf:rfc:3986"/>
		<value value="urn:oid:1.2.276.0.7230010.3.1.4.2139363186.8948.974458937.72"/>
	</masterIdentifier>
	<status value="current"/>
	<type>
		<!-- 11538-6, LOINC, "CT Chest Report -->
		<coding>
			<system value="http://loinc.org"/>
			<code value="11538-6"/>
			<display value="CT Chest Report"/>
		</coding>
	</type>
	<!-- NOT in the data set -->
	<indexed value="2000-11-17T12:02:17+01:00"/>
	<content>
	<!-- check if an empty attachment element is allowed -->
		<attachment>
		<!-- NOT in the data set -->
			<title value="CT Chest Report"/>
		</attachment>
	</content>
</DocumentReference>
